rolling_dice/__init__.py
rolling_dice/models/Dice.py
rolling_dice/models/Result.py
rolling_dice/models/__init__.py
rolling_dice/models/errors/DiceError.py
rolling_dice/models/errors/NotFoundMethod.py
rolling_dice/models/errors/ParseError.py
rolling_dice/models/errors/__init__.py
rolling_dice/parser/__init__.py
rolling_dice/parser/get_result.py
rolling_dice/parser/lark_laboers.py
rolling_dice/resources/__init__.py
rolling_dice/resources/grammar.py
rolling_dice-1.2.dist-info/LICENSE
rolling_dice-1.2.dist-info/METADATA
rolling_dice-1.2.dist-info/WHEEL
rolling_dice-1.2.dist-info/top_level.txt
rolling_dice-1.2.dist-info/RECORD
